pacotepypi001/modulo.py
pacotepypi001-0.0.1.dist-info/LICENSE
pacotepypi001-0.0.1.dist-info/METADATA
pacotepypi001-0.0.1.dist-info/WHEEL
pacotepypi001-0.0.1.dist-info/top_level.txt
pacotepypi001-0.0.1.dist-info/RECORD
