Metadata-Version: 2.1
Name: pacotepypi001
Version: 0.0.1
Summary: Pacote python para exibir número de 1 a 9
Home-page: https://github.com/marcos-de-sousa/pacotepypi
Author: João Vitor Cardoso Queiroz
Author-email: jvcq15@outlook.com
License: MIT License
Keywords: Pacote
License-File: LICENSE
Requires-Dist: numpy
